{"cameraMode":{"drawMode":0,"name":"Shaded","section":"Shading Mode"},"sceneLighting":true,"audioPlay":false,"sceneViewState":{"m_AlwaysRefresh":false,"showFog":true,"showSkybox":true,"showFlares":true,"showImageEffects":true,"showParticleSystems":true,"showVisualEffectGraphs":true,"m_FxEnabled":true},"in2DMode":false,"pivot":{"x":0.06524191796779633,"y":2.532825469970703,"z":-7.9976606369018559},"rotation":{"x":-0.2096983641386032,"y":-0.06975117325782776,"z":0.0149923637509346,"w":-0.9751807451248169},"size":0.9661238789558411,"orthographic":false}